README.md
setup.cfg
setup.py
channels_tools/__init__.py
channels_tools/authentication.py
channels_tools.egg-info/PKG-INFO
channels_tools.egg-info/SOURCES.txt
channels_tools.egg-info/dependency_links.txt
channels_tools.egg-info/requires.txt
channels_tools.egg-info/top_level.txt